sq_native/__about__.py
sq_native/__init__.py
sq_native/_bindings.py
sq_native/_compat.py
sq_native/_ffi.py
sq_native/input.py
sq_native/libSqreen.glibc.so
sq_native/waf.py
sq_native-1.1.2.0.0.dist-info/METADATA
sq_native-1.1.2.0.0.dist-info/WHEEL
sq_native-1.1.2.0.0.dist-info/top_level.txt
sq_native-1.1.2.0.0.dist-info/RECORD
