Metadata-Version: 2.1
Name: sq-native
Version: 1.1.2.0.0
Summary: Native module for the Python agent
Home-page: https://www.sqreen.com
Author: Sqreen
Author-email: support@sqreen.com
License: proprietary
Platform: UNKNOWN
Classifier: Development Status :: 5 - Production/Stable
Classifier: License :: Other/Proprietary License
Classifier: Programming Language :: Python :: 2.7
Classifier: Programming Language :: Python :: 3
Classifier: Topic :: Security
